[{
    "title": "Nuestros auspiciadores",
    "logos": [
      {
        "name": "Universidad Inca Garcilaso de la Vega",
        "url": "",
        "logoUrl": "../images/partners/uigv.png"
      },
      {
        "name": "GDG Open",
        "url": "",
        "logoUrl": "../images/partners/gdgopen.png"
      },
      {
        "name": "WTM",
        "url": "",
        "logoUrl": "../images/partners/wtm.png"
      },
      {
        "name": "GDG Cusco",
        "url": "",
        "logoUrl": "../images/partners/gdgcusco.png"
      },
      {
        "name": "GDG Cochabamba",
        "url": "",
        "logoUrl": "../images/partners/gdgcochabamba.png"
      },
      {
        "name": "Belatrix",
        "url": "",
        "logoUrl": "../images/partners/belatrix.png"
      },
      {
        "name": "Coslig",
        "url": "",
        "logoUrl": "../images/partners/coslig.png"
      },
      {
        "name": "GoLang Lima",
        "url": "",
        "logoUrl": "../images/partners/golanglima.png"
      },
      {
        "name": "React Lima",
        "url": "",
        "logoUrl": "../images/partners/reactlima.png"
      }
    ]
}]
